wmctrl.py
wmctrl-0.5.dist-info/LICENSE
wmctrl-0.5.dist-info/METADATA
wmctrl-0.5.dist-info/WHEEL
wmctrl-0.5.dist-info/top_level.txt
wmctrl-0.5.dist-info/RECORD
