Metadata-Version: 2.1
Name: wmctrl
Version: 0.5
Summary: A tool to programmatically control windows inside X
Author-email: Antonio Cuni <anto.cuni@gmail.com>
License: MIT
Project-URL: Homepage, https://github.com/antocuni/wmctrl
Classifier: Development Status :: 5 - Production/Stable
Classifier: Intended Audience :: Developers
Classifier: License :: OSI Approved :: MIT License
Classifier: Programming Language :: Python
Classifier: Programming Language :: Python :: 2.7
Classifier: Programming Language :: Python :: 3.8
Classifier: Programming Language :: Python :: 3.9
Classifier: Programming Language :: Python :: 3.10
Classifier: Programming Language :: Python :: 3.11
Classifier: Programming Language :: Python :: 3.12
Requires-Python: >=2.7
License-File: LICENSE
Requires-Dist: attrs
Provides-Extra: test
Requires-Dist: pytest; extra == "test"
